jrpyml/__init__.py
jrpyml/__version__.py
jrpyml/datasets/__init__.py
jrpyml/datasets/data/beauty.zip
jrpyml/datasets/data/bond.zip
jrpyml/datasets/data/chopsticks.zip
jrpyml/datasets/data/chopsticks_full.zip
jrpyml/datasets/data/correlation.zip
jrpyml/datasets/data/head_size.zip
jrpyml/datasets/data/movies.zip
jrpyml/datasets/data/starbucks.zip
jrpyml/datasets/data/titanic.zip
jrpyml/datasets/data/usarrests.zip
jrpyml/get_numeric_list.py
jrpyml/vignettes.py
jrpyml-1.0.2.dist-info/METADATA
jrpyml-1.0.2.dist-info/WHEEL
jrpyml-1.0.2.dist-info/RECORD
