Metadata-Version: 2.1
Name: jrpyml
Version: 1.0.2
Summary: Jumping Rivers: Machine Learning with Python
Author: Jumping Rivers
Author-email: info@jumpingrivers.com
Requires-Python: >=3.8,<3.11
Classifier: Programming Language :: Python :: 3
Classifier: Programming Language :: Python :: 3.8
Classifier: Programming Language :: Python :: 3.9
Classifier: Programming Language :: Python :: 3.10
Requires-Dist: graphviz (>=0.20,<0.21)
Requires-Dist: matplotlib (>=3.5.2,<4.0.0)
Requires-Dist: numpy (>=1.23.0,<2.0.0)
Requires-Dist: pandas (>=1.4.3,<2.0.0)
Requires-Dist: scikit-learn (>=1.1.1,<2.0.0)
Requires-Dist: scipy (>=1.8.1,<2.0.0)
Requires-Dist: seaborn (>=0.11.2,<0.12.0)
